MANIFEST.in
requirements.txt
setup.py
shuriken/__init__.py
shuriken/agent.py
shuriken/example_config.json
shuriken/tests.py
shuriken.egg-info/PKG-INFO
shuriken.egg-info/SOURCES.txt
shuriken.egg-info/dependency_links.txt
shuriken.egg-info/requires.txt
shuriken.egg-info/top_level.txt