Metadata-Version: 1.0
Name: shuriken
Version: 0.1.4
Summary: Shuriken is a monitoring agent which allows to do passive checks for Shinken monitoring system vie mod-ws-arbiter.
Home-page: https://github.com/prawn-cake/shuriken.git
Author: prawn-cake
Author-email: ekimovsky.maksim@gmail.com
License: MIT
Platform: UNKNOWN
